makefourcc.py
makefourcc-1.0.1.dist-info/licenses/LICENSE
makefourcc-1.0.1.dist-info/METADATA
makefourcc-1.0.1.dist-info/WHEEL
makefourcc-1.0.1.dist-info/top_level.txt
makefourcc-1.0.1.dist-info/RECORD
